chris/__init__.py
chris/app/__init__.py
chris/app/app.py
chris/app/env_setting.py
chris/app/logging_utilities.py
chris/app/routes/__init__.py
chris/app/routes/archive_routes.py
chris/app/routes/info_routes.py
chris/app/routes/media_routes.py
chris/app/routes/outdoor_routes.py
chris/app/routes/post_routes.py
chris/app/routes/professional_routes.py
chris/app/routes/project_routes.py
chris/app/routes/recipe_routes.py
chris/app/routes/surveys_routes.py
chris/app/templates/index.html
chris/cli/__init__.py
chris/cli/main.py
chris/datasets/__init__.py
chris/datasets/data/archive/archive.json
chris/datasets/data/blog/podcast-episodes.json
chris/datasets/data/blog/posts-simple.json
chris/datasets/data/blog/posts.json
chris/datasets/data/cooking/recipes.json
chris/datasets/data/media/books.json
chris/datasets/data/media/movies.json
chris/datasets/data/media/podcasts.json
chris/datasets/data/media/tv-shows.json
chris/datasets/data/media/youtube-channels.json
chris/datasets/data/outdoor/cycling-routes.json
chris/datasets/data/outdoor/hiking-routes.json
chris/datasets/data/outdoor/running-routes.json
chris/datasets/data/professional/courses.json
chris/datasets/data/professional/jobs.json
chris/datasets/data/projects/projects.json
chris/datasets/data/surveys/surveys.json
chris/datasets/dataset_format.py
chris/datasets/dataset_info.py
chris/datasets/datasets.py
chris/datasets/fetch.py
chris/utilities/__init__.py
chris/utilities/generate_uuid.py
chris/validation/__init__.py
chris/validation/constraints/__init__.py
chris/validation/constraints/monotone_increase_constraint.py
chris/validation/schemas/books-schema.json
chris/validation/schemas/courses-schema.json
chris/validation/schemas/hiking-routes-schema.json
chris/validation/schemas/jobs-schema.json
chris/validation/schemas/posts-schema.json
chris/validation/schemas/projects-schema.json
chris/validation/validate.py
chris-1.1.0.dist-info/WHEEL
chris-1.1.0.dist-info/entry_points.txt
chris-1.1.0.dist-info/LICENSE.txt
chris-1.1.0.dist-info/METADATA
chris-1.1.0.dist-info/RECORD
